launchdarkly_api/__init__.py
launchdarkly_api/api_client.py
launchdarkly_api/api_response.py
launchdarkly_api/configuration.py
launchdarkly_api/exceptions.py
launchdarkly_api/py.typed
launchdarkly_api/rest.py
launchdarkly_api/api/__init__.py
launchdarkly_api/api/access_tokens_api.py
launchdarkly_api/api/account_members_api.py
launchdarkly_api/api/account_usage_beta_api.py
launchdarkly_api/api/ai_configs_beta_api.py
launchdarkly_api/api/announcements_api.py
launchdarkly_api/api/applications_beta_api.py
launchdarkly_api/api/approvals_api.py
launchdarkly_api/api/approvals_beta_api.py
launchdarkly_api/api/audit_log_api.py
launchdarkly_api/api/code_references_api.py
launchdarkly_api/api/context_settings_api.py
launchdarkly_api/api/contexts_api.py
launchdarkly_api/api/custom_roles_api.py
launchdarkly_api/api/data_export_destinations_api.py
launchdarkly_api/api/environments_api.py
launchdarkly_api/api/experiments_api.py
launchdarkly_api/api/feature_flags_api.py
launchdarkly_api/api/feature_flags_beta_api.py
launchdarkly_api/api/flag_import_configurations_beta_api.py
launchdarkly_api/api/flag_links_beta_api.py
launchdarkly_api/api/flag_triggers_api.py
launchdarkly_api/api/follow_flags_api.py
launchdarkly_api/api/holdouts_beta_api.py
launchdarkly_api/api/insights_charts_beta_api.py
launchdarkly_api/api/insights_deployments_beta_api.py
launchdarkly_api/api/insights_flag_events_beta_api.py
launchdarkly_api/api/insights_pull_requests_beta_api.py
launchdarkly_api/api/insights_repositories_beta_api.py
launchdarkly_api/api/insights_scores_beta_api.py
launchdarkly_api/api/integration_audit_log_subscriptions_api.py
launchdarkly_api/api/integration_delivery_configurations_beta_api.py
launchdarkly_api/api/integrations_beta_api.py
launchdarkly_api/api/layers_api.py
launchdarkly_api/api/metrics_api.py
launchdarkly_api/api/metrics_beta_api.py
launchdarkly_api/api/o_auth2_clients_api.py
launchdarkly_api/api/other_api.py
launchdarkly_api/api/persistent_store_integrations_beta_api.py
launchdarkly_api-20.0.0.dist-info/LICENSE.txt
launchdarkly_api-20.0.0.dist-info/METADATA
launchdarkly_api-20.0.0.dist-info/WHEEL
launchdarkly_api-20.0.0.dist-info/top_level.txt
launchdarkly_api-20.0.0.dist-info/RECORD
