Metadata-Version: 2.1
Name: launchdarkly-api
Version: 20.0.0
Summary: LaunchDarkly REST API
Home-page: 
Author: LaunchDarkly Technical Support Team
Author-email: LaunchDarkly Technical Support Team <support@launchdarkly.com>
License: Apache 2.0
Project-URL: Repository, https://github.com/launchdarkly/api-client-python
Keywords: OpenAPI,OpenAPI-Generator,LaunchDarkly REST API
Requires-Python: >=3.9
License-File: LICENSE.txt
Requires-Dist: pydantic >=2
Requires-Dist: python-dateutil >=2.8.2
Requires-Dist: typing-extensions >=4.7.1
Requires-Dist: urllib3 <3.0.0,>=2.1.0
